<?xml version="1.0" encoding="utf-8"?>
<class id="0946be3e-890f-471e-91d4-1e2295218ea5" type="Solution Folder" typeId="0dc2b846-c968-49eb-99b7-8776919313a8">
  <name>3 - Domain</name>
  <display>3 - Domain</display>
  <externalReference>9bb4214b-c7f4-4a07-ba31-0c8d9d826541</externalReference>
  <isAbstract>false</isAbstract>
  <sort-children>by-type-then-by-name</sort-children>
  <genericTypes />
  <isMapped>false</isMapped>
  <parentFolderId>a2134b53-6294-4bde-bd01-889ff096d875</parentFolderId>
  <packageId>af2c33bc-3a28-4b9b-9221-f101b7dd1a84</packageId>
  <packageName>Nullbox.Security</packageName>
  <stereotypes />
  <metadata />
  <childElements />
</class>